fishbowl/__init__.py
fishbowl/axes.py
fishbowl/base.py
fishbowl/color.py
fishbowl/core.py
fishbowl/decorator.py
fishbowl/draw.py
fishbowl/font.py
fishbowl/config/fishbowl.axes.json
fishbowl/config/fishbowl.palettes.json
fishbowl-0.3.1.dist-info/DESCRIPTION.rst
fishbowl-0.3.1.dist-info/METADATA
fishbowl-0.3.1.dist-info/RECORD
fishbowl-0.3.1.dist-info/WHEEL
fishbowl-0.3.1.dist-info/metadata.json
fishbowl-0.3.1.dist-info/top_level.txt
