Metadata-Version: 2.0
Name: fishbowl
Version: 0.3.1
Summary: Customizable matplotlib style extension
Home-page: https://github.com/baxen/fishbowl
Author: Bradley Axen
Author-email: bradley.axen@gmail.com
License: MIT
Keywords: style plotting matplotlib
Platform: UNKNOWN
Classifier: Development Status :: 3 - Alpha
Classifier: Topic :: Scientific/Engineering :: Visualization
Classifier: License :: OSI Approved :: MIT License
Classifier: Programming Language :: Python :: 2
Classifier: Programming Language :: Python :: 3
Classifier: Programming Language :: Python :: 2.7
Classifier: Programming Language :: Python :: 3.3
Classifier: Programming Language :: Python :: 3.4
Classifier: Programming Language :: Python :: 3.5
Requires-Dist: matplotlib (>=2.0.0)
